wispylib/__init__.py
wispylib/core.py
wispylib-0.2.2.dist-info/licenses/LICENCE
wispylib-0.2.2.dist-info/METADATA
wispylib-0.2.2.dist-info/WHEEL
wispylib-0.2.2.dist-info/entry_points.txt
wispylib-0.2.2.dist-info/top_level.txt
wispylib-0.2.2.dist-info/RECORD
