Metadata-Version: 2.4
Name: wispylib
Version: 0.2.2
Summary: A link scraping and redirect-checking utility
Author: Ryu saiki
Author-email: your.email@example.com
Classifier: Programming Language :: Python :: 3
Classifier: License :: OSI Approved :: MIT License
Requires-Python: >=3.7
License-File: LICENCE
Requires-Dist: requests
Requires-Dist: beautifulsoup4
Requires-Dist: tldextract
Dynamic: author
Dynamic: author-email
Dynamic: classifier
Dynamic: description
Dynamic: description-content-type
Dynamic: license-file
Dynamic: requires-dist
Dynamic: requires-python
Dynamic: summary
